tempo/__init__.py
tempo/conf.py
tempo/errors.py
tempo/magic.py
tempo/mlserver.py
tempo/utils.py
tempo/version.py
tempo/aio/__init__.py
tempo/aio/deploy.py
tempo/aio/mixin.py
tempo/aio/model.py
tempo/aio/pipeline.py
tempo/aio/utils.py
tempo/docker/__init__.py
tempo/docker/constants.py
tempo/docker/utils.py
tempo/examples/__init__.py
tempo/examples/minio.py
tempo/ingress/__init__.py
tempo/ingress/istio.py
tempo/insights/__init__.py
tempo/insights/cloudevents.py
tempo/insights/manager.py
tempo/insights/worker.py
tempo/insights/wrapper.py
tempo/k8s/__init__.py
tempo/k8s/constants.py
tempo/k8s/utils.py
tempo/metaflow/__init__.py
tempo/metaflow/utils.py
tempo/protocols/__init__.py
tempo/protocols/seldon.py
tempo/protocols/tensorflow.py
tempo/protocols/v2.py
tempo/seldon/__init__.py
tempo/seldon/constants.py
tempo/seldon/deploy.py
tempo/seldon/docker.py
tempo/seldon/endpoint.py
tempo/seldon/k8s.py
tempo/seldon/specs.py
tempo/serve/__init__.py
tempo/serve/args.py
tempo/serve/base.py
tempo/serve/constants.py
tempo/serve/deploy.py
tempo/serve/ingress.py
tempo/serve/metadata.py
tempo/serve/model.py
tempo/serve/pipeline.py
tempo/serve/protocol.py
tempo/serve/stub.py
tempo/serve/types.py
tempo/serve/typing.py
tempo/serve/utils.py
tempo/serve/loader/__init__.py
tempo/serve/loader/artifact.py
tempo/serve/loader/env.py
tempo/serve/loader/upload.py
tempo/state/__init__.py
tempo/state/state.py
tests/__init__.py
tests/conftest.py
tests/test_mlserver.py
tests/test_mlserver_cases.py
tests/aio/__init__.py
tests/aio/conftest.py
tests/aio/test_model.py
tests/aio/test_pipeline.py
tests/protocols/__init__.py
tests/protocols/test_v2.py
tests/seldon/__init__.py
tests/seldon/test_deploy.py
tests/seldon/test_specs.py
tests/seldon/docker/__init__.py
tests/seldon/docker/conftest.py
tests/seldon/docker/test_model.py
tests/seldon/docker/test_pipeline.py
tests/seldon/docker/test_tensorflow.py
tests/seldon/k8s/__init__.py
tests/seldon/k8s/conftest.py
tests/seldon/k8s/test_k8s.py
mlops_tempo-0.5.2.dist-info/LICENSE
mlops_tempo-0.5.2.dist-info/METADATA
mlops_tempo-0.5.2.dist-info/WHEEL
mlops_tempo-0.5.2.dist-info/top_level.txt
mlops_tempo-0.5.2.dist-info/RECORD
