Metadata-Version: 2.1
Name: mlops-tempo
Version: 0.5.2
Summary: Machine Learning Operations Toolkit
Home-page: https://github.com/SeldonIO/tempo
Author: Seldon Technologies Ltd.
Author-email: hello@seldon.io
License: Apache 2.0
Platform: UNKNOWN
Requires-Python: >=3.7
Requires-Dist: grpcio (>=1.32.0)
Requires-Dist: protobuf (>=3.14.0)
Requires-Dist: attrs
Requires-Dist: numpy
Requires-Dist: kubernetes
Requires-Dist: docker
Requires-Dist: packaging
Requires-Dist: aiohttp
Requires-Dist: requests
Requires-Dist: pydantic
Requires-Dist: cloudpickle
Requires-Dist: python-rclone
Requires-Dist: seldon-deploy-sdk
Requires-Dist: conda-pack
Requires-Dist: mlserver
Requires-Dist: janus
Requires-Dist: redis
